pydantic_rdf/__init__.py
pydantic_rdf/annotation.py
pydantic_rdf/exceptions.py
pydantic_rdf/model.py
pydantic_rdf/py.typed
pydantic_rdf/types.py
pydantic_rdf-0.2.0.dist-info/METADATA
pydantic_rdf-0.2.0.dist-info/WHEEL
pydantic_rdf-0.2.0.dist-info/RECORD
