Metadata-Version: 2.4
Name: pydantic-rdf
Version: 0.2.0
Summary: Bridge between Pydantic V2 models and RDF graphs
Project-URL: Documentation, https://omegaice.github.io/pydantic-rdf
Project-URL: Repository, https://github.com/Omegaice/pydantic-rdf
Project-URL: Changelog, https://github.com/Omegaice/pydantic-rdf/blob/main/CHANGELOG.md
Project-URL: Issues, https://github.com/Omegaice/pydantic-rdf/issues
Author-email: Omegaice <950526+Omegaice@users.noreply.github.com>
Keywords: graph,linked data,pydantic,rdf,semantic web,serialization
Classifier: Development Status :: 4 - Beta
Classifier: Intended Audience :: Developers
Classifier: License :: OSI Approved :: MIT License
Classifier: Programming Language :: Python :: 3
Classifier: Programming Language :: Python :: 3.11
Classifier: Topic :: Scientific/Engineering :: Information Analysis
Classifier: Topic :: Software Development :: Libraries :: Python Modules
Classifier: Topic :: Utilities
Classifier: Typing :: Typed
Requires-Python: >=3.11
Requires-Dist: pydantic>=2.11.3
Requires-Dist: rdflib>=7.1.4
